<?xml version="1.0" encoding="utf-8" ?>
<dwsync>
<file name="arrow.png" server="50.97.48.229/public_html/pincelatomico/" local="130499138431899498" remote="130643433600000000" Dst="2" />
<file name="bub.png" server="50.97.48.229/public_html/pincelatomico/" local="130499138431499381" remote="130643433600000000" Dst="2" />
<file name="close.gif" server="50.97.48.229/public_html/pincelatomico/" local="130499138425097055" remote="130643433600000000" Dst="2" />
<file name="error.png" server="50.97.48.229/public_html/pincelatomico/" local="130499138424832401" remote="130643433600000000" Dst="2" />
<file name="home.png" server="50.97.48.229/public_html/pincelatomico/" local="130499138417979985" remote="130643433600000000" Dst="2" />
<file name="logo-cedtec.png" server="50.97.48.229/public_html/pincelatomico/" local="130499138417809926" remote="130643433600000000" Dst="2" />
<file name="logo-color.png" server="50.97.48.229/public_html/pincelatomico/" local="130499138410997436" remote="130643433600000000" Dst="2" />
<file name="logo_pincel_branca.png" server="50.97.48.229/public_html/pincelatomico/" local="130499138410797365" remote="130643433600000000" Dst="2" />
<file name="notice.png" server="50.97.48.229/public_html/pincelatomico/" local="130499138403233749" remote="130643433600000000" Dst="2" />
<file name="success.png" server="50.97.48.229/public_html/pincelatomico/" local="130499138403113721" remote="130643433600000000" Dst="2" />
<file name="top1.png" server="50.97.48.229/public_html/pincelatomico/" local="130499138395390885" remote="130643433600000000" Dst="2" />
<file name="top2.png" server="50.97.48.229/public_html/pincelatomico/" local="130499138395180822" remote="130643433600000000" Dst="2" />
<file name="top3.png" server="50.97.48.229/public_html/pincelatomico/" local="130499138388085033" remote="130643433600000000" Dst="2" />
<file name="top4.png" server="50.97.48.229/public_html/pincelatomico/" local="130499138388195074" remote="130643433600000000" Dst="2" />
<file name="top5.png" server="50.97.48.229/public_html/pincelatomico/" local="130499138381342611" remote="130643433600000000" Dst="2" />
<file name="warning.png" server="50.97.48.229/public_html/pincelatomico/" local="130499138381232591" remote="130643433600000000" Dst="2" />
</dwsync>